fastmarkdocs/__init__.py
fastmarkdocs/code_samples.py
fastmarkdocs/documentation_loader.py
fastmarkdocs/endpoint_analyzer.py
fastmarkdocs/exceptions.py
fastmarkdocs/linter.py
fastmarkdocs/linter_cli.py
fastmarkdocs/openapi_enhancer.py
fastmarkdocs/py.typed
fastmarkdocs/scaffolder.py
fastmarkdocs/scaffolder_cli.py
fastmarkdocs/types.py
fastmarkdocs/utils.py
fastmarkdocs-0.5.0.dist-info/METADATA
fastmarkdocs-0.5.0.dist-info/WHEEL
fastmarkdocs-0.5.0.dist-info/entry_points.txt
fastmarkdocs-0.5.0.dist-info/licenses/LICENSE
fastmarkdocs-0.5.0.dist-info/RECORD
