Metadata-Version: 2.4
Name: fastmarkdocs
Version: 0.5.0
Summary: A powerful library for enhancing FastAPI applications with rich markdown-based API documentation
License: MIT
License-File: LICENSE
Keywords: fastapi,markdown,documentation,openapi,api,docs
Author: Dan Vatca
Author-email: dan.vatca@gmail.com
Requires-Python: >=3.9.2,<4.0
Classifier: Development Status :: 4 - Beta
Classifier: Framework :: FastAPI
Classifier: Intended Audience :: Developers
Classifier: License :: OSI Approved :: MIT License
Classifier: Operating System :: OS Independent
Classifier: Programming Language :: Python :: 3
Classifier: Programming Language :: Python :: 3.10
Classifier: Programming Language :: Python :: 3.11
Classifier: Programming Language :: Python :: 3.12
Classifier: Programming Language :: Python :: 3.13
Classifier: Programming Language :: Python :: 3.14
Classifier: Programming Language :: Python :: 3.9
Classifier: Topic :: Internet :: WWW/HTTP :: HTTP Servers
Classifier: Topic :: Software Development :: Documentation
Classifier: Topic :: Software Development :: Libraries :: Python Modules
Requires-Dist: fastapi (>=0.68.0)
Requires-Dist: mistune (>=2.0.0)
Requires-Dist: pathvalidate (>=3.2.3,<4.0.0)
Requires-Dist: pydantic (>=1.8.0)
Requires-Dist: pyyaml (>=5.4.0)
Requires-Dist: starlette (>=0.40.0)
Project-URL: Bug Tracker, https://github.com/danvatca/fastmarkdocs/issues
Project-URL: Changelog, https://github.com/danvatca/fastmarkdocs/blob/main/CHANGELOG.md
Project-URL: Documentation, https://github.com/danvatca/fastmarkdocs
Project-URL: Homepage, https://github.com/danvatca/fastmarkdocs
Project-URL: Repository, https://github.com/danvatca/fastmarkdocs
